numberandchinese/__init__.py
numberandchinese/numberandchinese.py
numberandchinese-1.0.2.dist-info/LICENSE
numberandchinese-1.0.2.dist-info/METADATA
numberandchinese-1.0.2.dist-info/WHEEL
numberandchinese-1.0.2.dist-info/top_level.txt
numberandchinese-1.0.2.dist-info/RECORD
