Metadata-Version: 2.1
Name: numberandchinese
Version: 1.0.2
Summary: 数字中文转换器
Home-page: https://github.com/lichenyichay/numberandchinese-Including/
Author: Chay
Author-email: chay <lichenyi_2020@qq.com>
Project-URL: Homepage, https://github.com/lichenyichay/numberandchinese-Including/
Project-URL: Issues, https://github.com/lichenyichay/numberandchinese-Including/issues
Classifier: Programming Language :: Python :: 3
Classifier: License :: OSI Approved :: MIT License
Classifier: Operating System :: OS Independent
Requires-Python: >=3.5
License-File: LICENSE
